.coveragerc
.gitignore
.travis.yml
CHANGELOG.md
COPYING
README.md
requirements.txt
setup.cfg
setup.py
test-py34.sh
.github/workflows/python-3.10.yml
.github/workflows/python-3.5.yml
.github/workflows/python-3.9.yml
aioax25/__init__.py
aioax25/frame.py
aioax25/interface.py
aioax25/kiss.py
aioax25/router.py
aioax25/signal.py
aioax25/unit.py
aioax25.egg-info/PKG-INFO
aioax25.egg-info/SOURCES.txt
aioax25.egg-info/dependency_links.txt
aioax25.egg-info/requires.txt
aioax25.egg-info/top_level.txt
aioax25/aprs/__init__.py
aioax25/aprs/aprs.py
aioax25/aprs/compression.py
aioax25/aprs/datatype.py
aioax25/aprs/datetime.py
aioax25/aprs/frame.py
aioax25/aprs/message.py
aioax25/aprs/position.py
aioax25/aprs/router.py
aioax25/aprs/symbol.py
aioax25/aprs/uidigi.py
tests/__init__.py
tests/asynctest.py
tests/conftest.py
tests/hex.py
tests/loop.py
tests/nosecompat.py
tests/test_unit.py
tests/fixtures/__init__.py
tests/fixtures/logger.py
tests/test_aprs/__init__.py
tests/test_aprs/test_aprs.py
tests/test_aprs/test_datetime.py
tests/test_aprs/test_frame.py
tests/test_aprs/test_message.py
tests/test_aprs/test_position.py
tests/test_aprs/test_router.py
tests/test_aprs/test_symbol.py
tests/test_aprs/test_uidigi.py
tests/test_frame/__init__.py
tests/test_frame/test_ax25address.py
tests/test_frame/test_ax25frame.py
tests/test_frame/test_ax25frameheader.py
tests/test_frame/test_ax25path.py
tests/test_interface/__init__.py
tests/test_interface/test_interface.py
tests/test_kiss/__init__.py
tests/test_kiss/test_base.py
tests/test_kiss/test_command.py
tests/test_kiss/test_factory.py
tests/test_kiss/test_port.py
tests/test_kiss/test_protocol.py
tests/test_kiss/test_serial.py
tests/test_kiss/test_subproc.py
tests/test_kiss/test_tcp.py
tests/test_signal/__init__.py
tests/test_signal/test_signal.py
tests/test_signal/test_slot.py