Metadata-Version: 2.1
Name: aioax25
Version: 0.0.11
Summary: Asynchronous AX.25 interface in pure Python using asyncio
Home-page: https://github.com/sjlongland/aioax25/
Author: Stuart Longland VK4MSL
Author-email: me@vk4msl.id.au
License: GPL-2.0-or-later
Classifier: Development Status :: 2 - Pre-Alpha
Classifier: Environment :: No Input/Output (Daemon)
Classifier: Framework :: AsyncIO
Classifier: Intended Audience :: Developers
Classifier: License :: OSI Approved :: GNU General Public License v2 or later (GPLv2+)
Classifier: Operating System :: POSIX
Classifier: Programming Language :: Python :: 3 :: Only
Classifier: Topic :: Communications :: Ham Radio
Requires: pyserial
Requires: signalslot
Requires: pyserial_asyncio
License-File: COPYING
